{
  "sections": {
    "main": {
      "type": "list-collections",
      "disabled": true,
      "blocks": {
        "539aa35c-673f-4b5f-990b-5a1dbdcc3b25": {
          "type": "collection",
          "settings": {
            "collection": "acne-and-blemishes"
          }
        }
      },
      "block_order": [
        "539aa35c-673f-4b5f-990b-5a1dbdcc3b25"
      ],
      "settings": {
        "wrapper": "full",
        "layout": "grid",
        "columns": 2,
        "height": 80,
        "text_size": 75,
        "title": "",
        "button_text": "Shop All",
        "button_style": "text",
        "bg_color": "",
        "text_color": "light",
        "overlay_opacity": 0,
        "enable_slider_mobile": true
      }
    },
    "16563374560bce2809": {
      "type": "section-mosaic",
      "blocks": {
        "1656337456cd304120-0": {
          "type": "image",
          "settings": {
            "image": "shopify:\/\/shop_images\/5462v4.jpg",
            "bg_position": "center-center",
            "overlay_opacity": 0,
            "text_position": "top-left",
            "subheading": "",
            "title": "shop by <br> category",
            "text": "",
            "button_text": "",
            "link": "shopify:\/\/pages\/by-category",
            "secondary_button_text": "",
            "secondary_button_link": "",
            "text_color": "text-dark"
          }
        },
        "0827f398-632c-49d0-a357-364b4a5cc04c": {
          "type": "text",
          "settings": {
            "text_position": "left",
            "subheading": "",
            "title": "build your custom travel size bundle",
            "text": "choose 3 travel size mini products",
            "button_text": "",
            "link": "shopify:\/\/collections\/same-travel",
            "secondary_button_text": "",
            "secondary_button_link": "",
            "text_color": "text-light",
            "bg_color": "#7a7a7a"
          }
        },
        "3f5ae3c6-4c2f-4cc2-b07c-7d4a98c8afe9": {
          "type": "text",
          "settings": {
            "text_position": "left",
            "subheading": "",
            "title": "shop by collection",
            "text": "",
            "button_text": "",
            "link": "shopify:\/\/pages\/by-collections",
            "secondary_button_text": "",
            "secondary_button_link": "",
            "text_color": "text-light",
            "bg_color": "#7a7a7a"
          }
        },
        "3b0465b8-dfb4-418d-a77f-83c17e05eb8d": {
          "type": "text",
          "settings": {
            "text_position": "left",
            "subheading": "",
            "title": "seasonal limited",
            "text": "limited quantities available",
            "button_text": "",
            "link": "shopify:\/\/collections\/seasonal-limited",
            "secondary_button_text": "",
            "secondary_button_link": "",
            "text_color": "text-light",
            "bg_color": "#7a7a7a"
          }
        },
        "1656337456cd304120-2": {
          "type": "image",
          "settings": {
            "image": "shopify:\/\/shop_images\/0312v4_1.jpg",
            "bg_position": "center-center",
            "overlay_opacity": 0,
            "text_position": "top-left",
            "subheading": "",
            "title": "shop by concern",
            "text": "",
            "button_text": "",
            "link": "shopify:\/\/pages\/by-concern",
            "secondary_button_text": "",
            "secondary_button_link": "",
            "text_color": "text-light"
          }
        }
      },
      "block_order": [
        "1656337456cd304120-0",
        "0827f398-632c-49d0-a357-364b4a5cc04c",
        "3f5ae3c6-4c2f-4cc2-b07c-7d4a98c8afe9",
        "3b0465b8-dfb4-418d-a77f-83c17e05eb8d",
        "1656337456cd304120-2"
      ],
      "settings": {
        "height": "750",
        "min_mobile_height": 230,
        "wrapper": "full",
        "add_spacing": true,
        "heading_size": 100,
        "button_style": "primary btn--small",
        "secondary_button_style": "secondary btn--small",
        "bg_color": "",
        "enable_slider_mobile": false
      }
    },
    "266331ec-3b1b-47b9-a284-7178be1628d7": {
      "type": "section-collection",
      "settings": {
        "collection": "all-products",
        "title": "",
        "description": "",
        "spacing_range": 0,
        "heading_alignment": false,
        "show_description": false,
        "products_rows": 11,
        "products_layout": "grid",
        "show_collection_button": false,
        "show_collection": "",
        "button_style": "text",
        "bg_color": "",
        "enable_slider_mobile": false,
        "remove_top_padding": false,
        "remove_margin_bottom": false
      }
    }
  },
  "order": [
    "main",
    "16563374560bce2809",
    "266331ec-3b1b-47b9-a284-7178be1628d7"
  ]
}